taskalchemy/__init__.py
taskalchemy-0.0.1.dist-info/LICENSE
taskalchemy-0.0.1.dist-info/METADATA
taskalchemy-0.0.1.dist-info/WHEEL
taskalchemy-0.0.1.dist-info/RECORD
