Metadata-Version: 2.1
Name: taskalchemy
Version: 0.0.1
Summary: PostgreSQL-backed Background Task System
License: MIT
Author: Cadu
Author-email: cadu.coelho@gmail.com
Requires-Python: >=3.12,<4.0
Classifier: License :: OSI Approved :: MIT License
Classifier: Programming Language :: Python :: 3
Classifier: Programming Language :: Python :: 3.12
Requires-Dist: psycopg2-binary (>=2.9.9,<3.0.0)
